vcue/basics.py
vcue/data.py
vcue/display.py
vcue/stats.py
vcue/visual.py
vcue/web.py
vcue_repo-0.1.0.dist-info/METADATA
vcue_repo-0.1.0.dist-info/WHEEL
vcue_repo-0.1.0.dist-info/entry_points.txt
vcue_repo-0.1.0.dist-info/top_level.txt
vcue_repo-0.1.0.dist-info/RECORD
