Metadata-Version: 2.1
Name: vcue-repo
Version: 0.1.0
Summary: basic functionality package for handling data
Home-page: https://github.com/losDaniel/VCUErepo.git
Author: Carlos Valcarcel
Author-email: losdaniel@berkeley.edu
License: unlicensed
Keywords: pandas data plotly scrape
Platform: UNKNOWN
Requires-Dist: pandas
Requires-Dist: numpy
Requires-Dist: bs4
Requires-Dist: matplotlib
Requires-Dist: plotly
Requires-Dist: sklearn
Requires-Dist: selenium
